fgtools/__init__.py
fgtools/aptdat.py
fgtools/btg.py
fgtools/dsf2stg_lookup.py
fgtools/fgelev.py
fgtools/aircraft/__init__.py
fgtools/aircraft/javaprop2jsbcpct.py
fgtools/aircraft/vsphist2jsbtable.py
fgtools/aircraft/vspstab2jsbtable.py
fgtools/geo/__init__.py
fgtools/geo/coord.py
fgtools/geo/rectangle.py
fgtools/math/__init__.py
fgtools/math/coord.py
fgtools/math/rectangle.py
fgtools/misc/__init__.py
fgtools/misc/coord_converter.py
fgtools/misc/scrape_emanualonline.py
fgtools/misc/scrape_scribd.py
fgtools/misc/tabletool.py
fgtools/scenery/__init__.py
fgtools/scenery/aptdat2airportsxml.py
fgtools/scenery/create_day_night_xml.py
fgtools/scenery/dsftxt2stg.py
fgtools/scenery/edit_stg.py
fgtools/scenery/fix_aptdat_icaos.py
fgtools/scenery/genws20.py
fgtools/scenery/osm2aptdat.py
fgtools/scenery/osmconf.ini
fgtools/scenery/pull_xplane_aptdat.py
fgtools/scenery/stg2ufo.py
fgtools/scenery/ungap_btg.py
fgtools/utils/__init__.py
fgtools/utils/binary.py
fgtools/utils/constants.py
fgtools/utils/files.py
fgtools/utils/interpolator.py
fgtools/utils/unit_convert.py
fgtools-2.1.27.dist-info/LICENSE
fgtools-2.1.27.dist-info/METADATA
fgtools-2.1.27.dist-info/WHEEL
fgtools-2.1.27.dist-info/entry_points.txt
fgtools-2.1.27.dist-info/top_level.txt
fgtools-2.1.27.dist-info/RECORD
