Metadata-Version: 2.1
Name: fgtools
Version: 2.1.27
Summary: Tools for FlightGear scenery generation and aircraft development
Home-page: https://github.com/TheFGFSEagle/fgtools
Author: TheFGFSEagle
Author-email: thefgfseagle@gmail.com
License: GPLv3
Project-URL: Homepage, https://github.com/TheFGFSEagle/fgtools
Project-URL: Bug Tracker, https://github.com/TheFGFSEagle/fgtools/issues
Keywords: flightgear
Classifier: Programming Language :: Python :: 3
License-File: LICENSE
Requires-Dist: scipy
Requires-Dist: shapely
Requires-Dist: pyproj
Requires-Dist: plum-dispatch <=1.7.4
Requires-Dist: tqdm
Requires-Dist: requests
Requires-Dist: appdirs
Requires-Dist: bs4
Requires-Dist: OSMPythonTools
Requires-Dist: Pillow
Requires-Dist: plum-dispatch
Requires-Dist: python-dateutil
Requires-Dist: natsort
Requires-Dist: importlib-resources ; python_version < "3.9"
